setuptools_git_details/__init__.py
setuptools_git_details/_git.py
setuptools_git_details/git.py
setuptools_git_details/logging.py
setuptools_git_details/main.py
setuptools_git_details-1.0.0.dist-info/LICENSE.txt
setuptools_git_details-1.0.0.dist-info/METADATA
setuptools_git_details-1.0.0.dist-info/WHEEL
setuptools_git_details-1.0.0.dist-info/entry_points.txt
setuptools_git_details-1.0.0.dist-info/top_level.txt
setuptools_git_details-1.0.0.dist-info/RECORD
