Metadata-Version: 2.1
Name: setuptools-git-details
Version: 1.0.0
Summary: A setuptools package to add details from git to your project.
Author-email: Marc Carré <carre.marc@gmail.com>
License: Apache License
Project-URL: Homepage, https://github.com/marccarre/setuptools-git-details
Project-URL: Documentation, https://github.com/marccarre/setuptools-git-details
Project-URL: Repository, https://github.com/marccarre/setuptools-git-details.git
Project-URL: Issues, https://github.com/marccarre/setuptools-git-details/issues
Project-URL: Changelog, https://github.com/marccarre/setuptools-git-details/blob/main/CHANGELOG.md
Classifier: Development Status :: 3 - Alpha
Classifier: Intended Audience :: Developers
Classifier: License :: OSI Approved :: Apache Software License
Classifier: Programming Language :: Python
Classifier: Programming Language :: Python :: 3 :: Only
Classifier: Programming Language :: Python :: 3.8
Classifier: Programming Language :: Python :: 3.9
Classifier: Programming Language :: Python :: 3.10
Classifier: Programming Language :: Python :: 3.11
Classifier: Programming Language :: Python :: 3.12
Classifier: Topic :: Software Development :: Libraries
Classifier: Topic :: Software Development :: Version Control
Classifier: Topic :: System :: Software Distribution
Classifier: Topic :: Utilities
Requires-Python: >=3.8
License-File: LICENSE.txt
Requires-Dist: setuptools >=75.1.0
Requires-Dist: tomli >=2.0.1 ; python_version < "3.11"
